car_drive_ai/__init__.py
car_drive_ai/main.py
car_drive_ai-1.0.9.dist-info/METADATA
car_drive_ai-1.0.9.dist-info/WHEEL
car_drive_ai-1.0.9.dist-info/top_level.txt
car_drive_ai-1.0.9.dist-info/RECORD
