Metadata-Version: 2.1
Name: car-drive-ai
Version: 1.0.9
Summary: with this package you can easily setup a car drive ai with pygame on you own raceing track
Home-page: https://github.com/timo42453189/car_drive_ai
Author: Timo Pickelmann
Author-email: timo.pickelmann.opensource@gmail.com
License: UNKNOWN
Platform: UNKNOWN
Requires-Dist: pygame
Requires-Dist: neat-python
Requires-Dist: numpy
Requires-Dist: matplotlib
Requires-Dist: wget
